mobility_db_api/__init__.py
mobility_db_api/api.py
mobility_db_api/csv_catalog.py
mobility_db_api/external_gtfs.py
mobility_db_api/logger.py
mobility_db_api/utils.py
mobility_db_api-0.5.1.dist-info/licenses/LICENSE
mobility_db_api-0.5.1.dist-info/METADATA
mobility_db_api-0.5.1.dist-info/WHEEL
mobility_db_api-0.5.1.dist-info/top_level.txt
mobility_db_api-0.5.1.dist-info/RECORD
