Metadata-Version: 2.4
Name: mobility-db-api
Version: 0.5.1
Summary: A Python client for the Mobility Database API
Author: Bence Damokos
Project-URL: Homepage, https://github.com/bdamokos/mobility-db-api
Project-URL: Bug Tracker, https://github.com/bdamokos/mobility-db-api/issues
Project-URL: Documentation, https://bdamokos.github.io/mobility-db-api/
Keywords: gtfs,public-transport,mobility,transit,open-data,transportation,api-client,mobility-database
Classifier: Development Status :: 3 - Alpha
Classifier: Intended Audience :: Developers
Classifier: License :: OSI Approved :: MIT License
Classifier: Operating System :: OS Independent
Classifier: Programming Language :: Python :: 3
Requires-Python: >=3.7
License-File: LICENSE
Requires-Dist: requests>=2.32.4
Requires-Dist: python-dotenv>=1.0.0
Requires-Dist: unidecode>=1.3.7
Provides-Extra: dev
Requires-Dist: pytest>=7.0.0; extra == "dev"
Requires-Dist: pytest-cov>=4.0.0; extra == "dev"
Requires-Dist: pytest-json-report>=1.5.0; extra == "dev"
Requires-Dist: black>=23.0.0; extra == "dev"
Requires-Dist: isort>=5.0.0; extra == "dev"
Requires-Dist: responses>=0.25.0; extra == "dev"
Dynamic: license-file
